README.md
setup.py
dev_ping_tester/AutoDetectDevice.py
dev_ping_tester/BaseDevice.py
dev_ping_tester/Cisco.py
dev_ping_tester/Huawei.py
dev_ping_tester/__init__.py
dev_ping_tester.egg-info/PKG-INFO
dev_ping_tester.egg-info/SOURCES.txt
dev_ping_tester.egg-info/dependency_links.txt
dev_ping_tester.egg-info/requires.txt
dev_ping_tester.egg-info/top_level.txt