Metadata-Version: 1.1
Name: dev-ping-tester
Version: 0.6
Summary: A automation framework to simplify automation tasks
Home-page: https://www.github.com/ljm625/dev_ping_tester
Author: Jiaming Li
Author-email: jiaminli@cisco.com
License: MIT
Download-URL: https://www.github.com/ljm625/dev_ping_tester/archive/v0.1.tar.gz
Keywords: AUTOMATION,CISCO
Platform: UNKNOWN
Classifier: Development Status :: 4 - Beta
Classifier: Intended Audience :: Developers
Classifier: Topic :: Software Development :: Libraries
Classifier: License :: OSI Approved :: MIT License
Classifier: Programming Language :: Python :: 2
Classifier: Programming Language :: Python :: 2.7
Classifier: Programming Language :: Python :: 3
Classifier: Programming Language :: Python :: 3.4
Classifier: Programming Language :: Python :: 3.5
Classifier: Programming Language :: Python :: 3.6
Classifier: Programming Language :: Python :: 3.7
Classifier: Programming Language :: Python :: 3.8
Classifier: Programming Language :: Python :: 3.9
